docshund/__init__.py
docshund/test_docshund.py
docshund-0.1.0.data/scripts/docshund
docshund-0.1.0.dist-info/LICENSE
docshund-0.1.0.dist-info/METADATA
docshund-0.1.0.dist-info/WHEEL
docshund-0.1.0.dist-info/top_level.txt
docshund-0.1.0.dist-info/RECORD
