Metadata-Version: 2.1
Name: docshund
Version: 0.1.0
Summary: docshund: a doc dog.
Home-page: https://github.com/FitMango/docshund
Author: Jordan Matelsky
Author-email: opensource@fitmango.com
License: Apache License 2.0
Platform: UNKNOWN
Classifier: License :: OSI Approved :: Apache Software License
Classifier: Programming Language :: Python
Classifier: Programming Language :: Python :: 3
Classifier: Programming Language :: Python :: 3.6
Requires-Python: >=3.6.0
Provides-Extra: dev
Requires-Dist: pytest ; extra == 'dev'
Requires-Dist: pylint ; extra == 'dev'
